tilted/__init__.py
tilted/constants.py
tilted/enums.py
tilted/exceptions.py
tilted/hand_evaluation.py
tilted/models.py
tilted/utils.py
tilted-0.1.4.dist-info/LICENSE
tilted-0.1.4.dist-info/WHEEL
tilted-0.1.4.dist-info/METADATA
tilted-0.1.4.dist-info/RECORD
