Metadata-Version: 2.1
Name: tilted
Version: 0.1.4
Summary: Tilted is a lightweight, open-source Python package with a simple interface for poker hand evaluation & comparison.
Home-page: https://github.com/MaxAtkinson/tilted
License: Apache-2.0
Keywords: poker,hand,card,deck,suit
Author: Max Atkinson
Author-email: hiremaxatkinson@gmail.com
Requires-Python: >=3.10,<4.0
Classifier: License :: OSI Approved :: Apache Software License
Classifier: Programming Language :: Python :: 3
Classifier: Programming Language :: Python :: 3.10
Project-URL: Repository, https://github.com/MaxAtkinson/tilted
